easykiwoom/__init__.py
easykiwoom/kiwoom_proxy.exe
easykiwoom/market/__init__.py
easykiwoom/market/market.py
easykiwoom/market/market_utils.py
easykiwoom/utils.py
easykiwoom-0.1.1.dist-info/LICENSE.txt
easykiwoom-0.1.1.dist-info/METADATA
easykiwoom-0.1.1.dist-info/WHEEL
easykiwoom-0.1.1.dist-info/RECORD
