Metadata-Version: 2.1
Name: easykiwoom
Version: 0.1.1
Summary: 쉽고 간편한 키움증권 API
License: GPL-3.0
Author: Park Junha
Author-email: junha5301@gmail.com
Requires-Python: >=3.10,<4.0
Classifier: License :: OSI Approved :: GNU General Public License v3 (GPLv3)
Classifier: Programming Language :: Python :: 3
Classifier: Programming Language :: Python :: 3.10
Classifier: Programming Language :: Python :: 3.11
Classifier: Programming Language :: Python :: 3.12
Requires-Dist: freezegun (>=1.5.1,<2.0.0)
Requires-Dist: mplfinance (>=0.12.10b0,<0.13.0)
Requires-Dist: psutil (>=6.1.1,<7.0.0)
